snippy_ng/__about__.py
snippy_ng/__init__.py
snippy_ng/__main__.py
snippy_ng/at_run_time.py
snippy_ng/dependencies.py
snippy_ng/exceptions.py
snippy_ng/logging.py
snippy_ng/seq_utils.py
snippy_ng/snippy.py
snippy_ng/cli/__init__.py
snippy_ng/cli/asm_cli.py
snippy_ng/cli/long_cli.py
snippy_ng/cli/short_cli.py
snippy_ng/cli/utils/__init__.py
snippy_ng/cli/utils/bug_catcher.py
snippy_ng/cli/utils/globals.py
snippy_ng/cli/utils/pipeline_runner.py
snippy_ng/pipelines/asm.py
snippy_ng/pipelines/common.py
snippy_ng/pipelines/long.py
snippy_ng/pipelines/short.py
snippy_ng/stages/__init__.py
snippy_ng/stages/alignment.py
snippy_ng/stages/base.py
snippy_ng/stages/calling.py
snippy_ng/stages/clean_reads.py
snippy_ng/stages/compression.py
snippy_ng/stages/consensus.py
snippy_ng/stages/consequences.py
snippy_ng/stages/copy.py
snippy_ng/stages/downsample_reads.py
snippy_ng/stages/filtering.py
snippy_ng/stages/masks.py
snippy_ng/stages/setup.py
snippy_ng/stages/stats.py
snippy_nextgen-1.14.0.dist-info/METADATA
snippy_nextgen-1.14.0.dist-info/WHEEL
snippy_nextgen-1.14.0.dist-info/entry_points.txt
snippy_nextgen-1.14.0.dist-info/licenses/LICENSE.txt
snippy_nextgen-1.14.0.dist-info/RECORD
