Metadata-Version: 2.4
Name: snippy-nextgen
Version: 1.14.0
Summary: The Next Generation of Microbial Variant Calling with Snippy
Project-URL: Documentation, https://github.com/centre-pathogen-genomics/snippy-ng#readme
Project-URL: Issues, https://github.com/centre-pathogen-genomics/snippy-ng/issues
Project-URL: Source, https://github.com/centre-pathogen-genomics/snippy-ng
Author-email: Wytamma Wirth <wytamma.wirth@me.com>
License-Expression: MIT
License-File: LICENSE.txt
Keywords: bioinformatics,genomics,microbial genomics,snippy,variant calling
Classifier: Development Status :: 4 - Beta
Classifier: Programming Language :: Python
Classifier: Programming Language :: Python :: 3.9
Classifier: Programming Language :: Python :: 3.10
Classifier: Programming Language :: Python :: 3.11
Classifier: Programming Language :: Python :: 3.12
Classifier: Programming Language :: Python :: 3.13
Classifier: Programming Language :: Python :: Implementation :: CPython
Classifier: Programming Language :: Python :: Implementation :: PyPy
Requires-Python: >=3.8
Requires-Dist: biopython
Requires-Dist: click
Requires-Dist: packaging
Requires-Dist: pydantic
